formancesdkauth/__init__.py
formancesdkauth/clients.py
formancesdkauth/sdk.py
formancesdkauth/sdkconfiguration.py
formancesdkauth/secrets.py
formancesdkauth/users.py
formancesdkauth/_hooks/__init__.py
formancesdkauth/_hooks/clientcredentials.py
formancesdkauth/_hooks/registration.py
formancesdkauth/_hooks/sdkhooks.py
formancesdkauth/_hooks/types.py
formancesdkauth/models/__init__.py
formancesdkauth/models/components/__init__.py
formancesdkauth/models/components/client.py
formancesdkauth/models/components/clientdata.py
formancesdkauth/models/components/schemeformanceoauth.py
formancesdkauth/models/components/secret.py
formancesdkauth/models/components/security.py
formancesdkauth/models/components/serverinfo.py
formancesdkauth/models/components/user.py
formancesdkauth/models/errors/__init__.py
formancesdkauth/models/errors/sdkerror.py
formancesdkauth/models/operations/__init__.py
formancesdkauth/models/operations/clients_create.py
formancesdkauth/models/operations/clients_delete.py
formancesdkauth/models/operations/clients_get.py
formancesdkauth/models/operations/clients_list.py
formancesdkauth/models/operations/clients_update.py
formancesdkauth/models/operations/secrets_create.py
formancesdkauth/models/operations/secrets_delete.py
formancesdkauth/models/operations/users_get.py
formancesdkauth/models/operations/users_list.py
formancesdkauth/utils/__init__.py
formancesdkauth/utils/retries.py
formancesdkauth/utils/utils.py
formance_sdk_auth-1.0.0a26.dist-info/METADATA
formance_sdk_auth-1.0.0a26.dist-info/WHEEL
formance_sdk_auth-1.0.0a26.dist-info/top_level.txt
formance_sdk_auth-1.0.0a26.dist-info/RECORD
