Metadata-Version: 2.1
Name: formance-sdk-auth
Version: 1.0.0a26
Summary: Python Client SDK Generated by Speakeasy
Home-page: https://github.com/formancehq/formance-sdk-python-next.git
Author: Formance
License: UNKNOWN
Platform: UNKNOWN
Requires-Python: >=3.8
Requires-Dist: certifi>=2023.7.22
Requires-Dist: charset-normalizer>=3.2.0
Requires-Dist: dataclasses-json>=0.6.4
Requires-Dist: idna>=3.4
Requires-Dist: jsonpath-python>=1.0.6
Requires-Dist: marshmallow>=3.19.0
Requires-Dist: mypy-extensions>=1.0.0
Requires-Dist: packaging>=23.1
Requires-Dist: python-dateutil>=2.8.2
Requires-Dist: requests>=2.31.0
Requires-Dist: six>=1.16.0
Requires-Dist: typing-inspect>=0.9.0
Requires-Dist: typing-extensions>=4.7.1
Requires-Dist: urllib3>=1.26.18
Provides-Extra: dev
Requires-Dist: pylint==3.1.0; extra == "dev"
